{"type": "bar", "data": {"labels": ["New"], "datasets": [{"label": "Average Purchases", "data": [0.14395886889460155, 0.0], "backgroundColor": ["#36A2EB", "#FF6384"], "borderColor": ["#36A2EB", "#FF6384"], "borderWidth": 1}]}, "options": {"scales": {"y": {"beginAtZero": true, "title": {"display": true, "text": "Average Purchase Rate"}}, "x": {"title": {"display": true, "text": "Visitor Type"}}}, "plugins": {"legend": {"display": true}, "title": {"display": true, "text": "Purchase Rate by Visitor Type"}}}}